daktylos/__init__.py
daktylos/data.py
daktylos/test_data.py
daktylos/rules/__init__.py
daktylos/rules/engine.py
daktylos/rules/status.py
daktylos-1.0.0.dist-info/METADATA
daktylos-1.0.0.dist-info/WHEEL
daktylos-1.0.0.dist-info/top_level.txt
daktylos-1.0.0.dist-info/RECORD
